AUTHORS.rst
CHANGELOG.rst
LICENSE.rst
MANIFEST.in
README.rst
pyproject.toml
setup.cfg
setup.py
versioneer.py
src/dataflow/__init__.py
src/dataflow/_version.py
src/dataflow/cli.py
src/dataflow/jobs.py
src/dataflow/operators.py
src/dataflow/task.py
src/dataflow/workflows.py
src/dataflow.egg-info/PKG-INFO
src/dataflow.egg-info/SOURCES.txt
src/dataflow.egg-info/dependency_links.txt
src/dataflow.egg-info/entry_points.txt
src/dataflow.egg-info/top_level.txt