Metadata-Version: 2.1
Name: dataflow
Version: 0.11.1
Summary: Simple API to define and trigger data analys
Home-page: https://dataflow.readthedocs.io
Author: Gabriel Jover-Manas
Author-email: gjover@cells.es
License: GPLv3
Classifier: Development Status :: 4 - Beta
Classifier: Intended Audience :: Science/Research
Classifier: Topic :: Scientific/Engineering
Classifier: License :: OSI Approved :: GNU General Public License v3 or later (GPLv3+)
Classifier: Natural Language :: English
Classifier: Programming Language :: Python :: 2.7
Classifier: Programming Language :: Python :: 3.7
Classifier: Programming Language :: Python :: 3.9
Classifier: Programming Language :: Python :: 3.10
License-File: LICENSE.rst
License-File: AUTHORS.rst
